ppm3/__init__.py
ppm3/main.py
ppm3/src/__init__.py
ppm3/src/constraints.py
ppm3/src/decorators.py
ppm3/src/freeze.py
ppm3/src/init.py
ppm3/src/install.py
ppm3/src/list.py
ppm3/src/loading.py
ppm3/src/manager.py
ppm3/src/outdated.py
ppm3/src/run.py
ppm3/src/uninstall.py
ppm3/src/update.py
ppm3-1.3.1.dist-info/METADATA
ppm3-1.3.1.dist-info/WHEEL
ppm3-1.3.1.dist-info/entry_points.txt
ppm3-1.3.1.dist-info/top_level.txt
ppm3-1.3.1.dist-info/RECORD
