Metadata-Version: 2.4
Name: ppm3
Version: 1.3.1
Summary: A Python project manager.
Home-page: https://github.com/rahulcodepython/Python-Project-Manager.git
Author: Rahul Das
Author-email: rahulcodepython@gmail.com
Project-URL: Bug Tracker, https://github.com/rahulcodepython/Python-Project-Manager/issues
Project-URL: Documentation, https://github.com/rahulcodepython/Python-Project-Manager/blob/main/ppm3/README.md
Project-URL: Source Code, https://github.com/rahulcodepython/Python-Project-Manager
Keywords: ppm,project manager,python package,python project manager
Classifier: Intended Audience :: Developers
Classifier: Programming Language :: Python :: 3
Classifier: Operating System :: OS Independent
Requires-Python: >=3.6
Requires-Dist: inquirer==3.4.0
Requires-Dist: setuptools==78.1.0
Requires-Dist: ruamel.yaml==0.18.10
Dynamic: author
Dynamic: author-email
Dynamic: classifier
Dynamic: description
Dynamic: description-content-type
Dynamic: home-page
Dynamic: keywords
Dynamic: project-url
Dynamic: requires-dist
Dynamic: requires-python
Dynamic: summary
